api6/Encryption.py
api6/__init__.py
api6/client.py
api6-3.1.0.dist-info/LICENCE
api6-3.1.0.dist-info/METADATA
api6-3.1.0.dist-info/WHEEL
api6-3.1.0.dist-info/top_level.txt
api6-3.1.0.dist-info/RECORD
