Metadata-Version: 2.1
Name: api6
Version: 3.1.0
Summary: Luis Rubika Bot to Rubika api 6
Home-page: https://guides.github.com/features/mastering-markdown/
Author: Luis
Author-email: mm12mok18@gmail.com
License: MIT
Classifier: Development Status :: 3 - Alpha
Classifier: Intended Audience :: Developers
Classifier: License :: OSI Approved :: MIT License
Classifier: Programming Language :: Python :: 3
License-File: LICENCE
